{
	"activities": {
		"activity1": {
			"name": "Take a walk",
			"time": "10 minutes",
			"cost": "$",
			"location": "outdoors",
			"description": "Take a walk! Find a park to walk through. If you don't have a park nearby, walk around your neighborhood."
		},
		"activity2": {
			"name": "Do a mini de-clutter",
			"time": "10 minutes",
			"cost": "$",
			"location": "indoors",
			"description": "Remove three things you no longer wear from your wardrobe to donate."
		},
		"activity3": {
			"name": "Visit a museum",
			"time": "90 minutes",
			"cost": "$",
			"location": "indoors",
			"description": "Take in an exhibit at a museum"
		},
		"activity4": {
			"name": "At home mini-spa",
			"time": "60 minutes",
			"cost": "$",
			"location": "indoors",
			"description": "Take a long bubble bath, give yourself a mani/pedi!"
		},
		"activity5": {
			"name": "Shake it out!",
			"time": "10 minutes",
			"cost": "$",
			"location": "indoors",
			"description": "Put on your favorite music and dance around your room!"
		},
		"activity6": {
			"name": "Naptime!",
			"time": "60 minutes",
			"cost": "$",
			"location": "indoors",
			"description": "Take a quick nap. You'll wake up feeling refreshed."
		},
		"activity7": {
			"name": "Meditate",
			"time": "10 minutes",
			"cost": "$",
			"location": "indoors",
			"description": "Take a moment(or more) to simply focus on breathing and being still."
		},
		"activity8": {
			"name": "Cloud-watch",
			"time": "20 minutes",
			"cost": "$",
			"location": "outdoors",
			"description": "Go outside, lie on your back, and watch the clouds."
		},
		"activity9": {
			"name": "Massage",
			"time": "60 minutes",
			"cost": "$$$",
			"location": "indoors",
			"description": "Book a relaxing massage"
		},
		"activity10": {
			"name": "Watch a movie",
			"time": "90 minutes",
			"cost": "$",
			"location": "indoors",
			"description": "Catch a movie in theaters, or curl up with Netflix"
		},
		"activity11": {
			"name": "Hiking",
			"time": "60 minutes",
			"cost": "$",
			"location": "outdoors",
			"description": "Go for a short(or long) hike!"
		},
		"activity12": {
			"name": "Yoga!",
			"time": "60 minutes",
			"cost": "$$",
			"location": "indoors",
			"description": "Take in a yoga class"
		},
		"activity13": {
			"name": "Get crafty!",
			"time": "30 minutes",
			"cost": "$",
			"location": "indoors",
			"description": "Knit, sculpt, paint, etc."
		},
		"activity14": {
			"name": "Tea",
			"time": "10 minutes",
			"cost": "$",
			"location": "indoors",
			"description": "Make a hot cup of tea."
		},
		"activity15": {
			"name": "Journal",
			"time": "15 minutes",
			"cost": "$",
			"location": "indoors",
			"description": "Take 15 minutes to write in a journal."
		}
	}

}